epochalyst/__init__.py
epochalyst/ensemble.py
epochalyst/model.py
epochalyst/caching/__init__.py
epochalyst/caching/cacher.py
epochalyst/data/__init__.py
epochalyst/data/enum_data_format.py
epochalyst/data/pipeline_dataset.py
epochalyst/logging/__init__.py
epochalyst/logging/logger.py
epochalyst/training/__init__.py
epochalyst/training/_custom_data_parallel.py
epochalyst/training/pretrain_block.py
epochalyst/training/torch_trainer.py
epochalyst/training/training.py
epochalyst/training/training_block.py
epochalyst/training/augmentation/__init__.py
epochalyst/training/augmentation/image_augmentations.py
epochalyst/training/augmentation/time_series_augmentations.py
epochalyst/training/augmentation/utils.py
epochalyst/training/models/__init__.py
epochalyst/training/models/conv1d_bn_relu.py
epochalyst/training/models/timm.py
epochalyst/training/utils/__init__.py
epochalyst/training/utils/get_dependencies.py
epochalyst/training/utils/recursive_repr.py
epochalyst/training/utils/tensor_functions.py
epochalyst/transformation/__init__.py
epochalyst/transformation/transformation.py
epochalyst/transformation/transformation_block.py
epochalyst-4.1.0.dist-info/METADATA
epochalyst-4.1.0.dist-info/WHEEL
epochalyst-4.1.0.dist-info/licenses/LICENSE
epochalyst-4.1.0.dist-info/RECORD
