Metadata-Version: 2.3
Name: epochalyst
Version: 4.1.0
Summary: Epochalyst is the base for Team Epoch competitions.
Project-URL: Homepage, https://teamepoch.ai/
Project-URL: Documentation, https://TeamEpochGithub.github.io/epochalyst/
Project-URL: Repository, https://github.com/TeamEpochGithub/epochalyst
Project-URL: Download, https://pypi.org/project/epochalyst/#files
Project-URL: Issues, https://github.com/TeamEpochGithub/epochalyst/issues
Project-URL: Release notes, https://github.com/TeamEpochGithub/epochalyst/releases
Author-email: Jasper van Selm <jmvanselm@gmail.com>, Ariel Ebersberger <arielebersberger@gmail.com>, Tolga Kopar <cahittolgakopar@gmail.com>, Jeffrey Lim <jeffrey-lim@outlook.com>, Hugo de Heer <hugodeheer1234@gmail.com>, Emiel Witting <emiel.witting@gmail.com>, Gregoire Dumont <dumont.gregoire.a@gmail.com>, Kristóf Sandor <emherk512@gmail.com>, Daniel De Dios Allegue <danieldediosallegue@gmail.com>
License: MIT License
License-File: LICENSE
Classifier: Intended Audience :: Developers
Classifier: License :: OSI Approved :: MIT License
Classifier: Operating System :: OS Independent
Classifier: Programming Language :: Python
Classifier: Programming Language :: Python :: 3
Classifier: Programming Language :: Python :: 3 :: Only
Classifier: Programming Language :: Python :: 3.10
Classifier: Programming Language :: Python :: 3.11
Classifier: Programming Language :: Python :: 3.12
Classifier: Typing :: Typed
Requires-Python: >=3.10
Requires-Dist: agogos>=0.4
Requires-Dist: annotated-types>=0.6.0
Requires-Dist: joblib>=1.4.0
Requires-Dist: numpy<3,>=1.22.4
Requires-Dist: torch>=2.1.0
Requires-Dist: typing-extensions>=4.9.0; python_version < '3.12'
Provides-Extra: audio
Requires-Dist: audiomentations>=0.36.0; extra == 'audio'
Provides-Extra: dask
Requires-Dist: dask-expr>=0.5.3; extra == 'dask'
Requires-Dist: dask[dataframe]>=2024.2.1; extra == 'dask'
Provides-Extra: image
Requires-Dist: kornia>=0.7.2; extra == 'image'
Requires-Dist: timm>=0.9.16; extra == 'image'
Provides-Extra: onnx
Requires-Dist: onnx>=1.16.1; extra == 'onnx'
Requires-Dist: onnxruntime>=1.18.0; extra == 'onnx'
Provides-Extra: openvino
Requires-Dist: openvino>=2024.2.0; extra == 'openvino'
Provides-Extra: pandas
Requires-Dist: pandas[parquet,performance]>=2.0.0; extra == 'pandas'
Provides-Extra: polars
Requires-Dist: polars>=0.20.22; extra == 'polars'
